tired/command.py
tired/datetime.py
tired/fs.py
tired/git.py
tired/logging.py
tired/meta.py
tired/parse.py
tired/serial.py
tired/shlex.py
tired/tk.py
tired/tmux.py
tired/ui.py
tired/ux.py
tired-0.3.7.dist-info/METADATA
tired-0.3.7.dist-info/WHEEL
tired-0.3.7.dist-info/top_level.txt
tired-0.3.7.dist-info/RECORD
