Metadata-Version: 2.1
Name: tired
Version: 0.3.7
Summary: Boilerplate I'm tired of writing over and over
Home-page: https://github.com/damurashov/TIRED
Author: Dmitry Murashov
License: MIT
Classifier: Programming Language :: Python :: 3
Classifier: License :: OSI Approved :: MIT License
Classifier: Operating System :: OS Independent
Requires-Python: >=3.7
Requires-Dist: simple-term-menu
Requires-Dist: datetime
Requires-Dist: pyserial
Requires-Dist: appdirs
